Easy_Bot/__init__.py
Easy_Bot/error/__init__.py
Easy_Bot/ext/__init__.py
Easy_Bot/ext/_client.py
Easy_Bot/ext/_commands.py
Easy_Bot/ext/_data_classess.py
Easy_Bot/ext/_publicIp.py
Easy_Bot/ext/_unauth.py
Easy_Bot/ext/_web.py
pg_easy_bot-0.2.6.dist-info/LICENSE
pg_easy_bot-0.2.6.dist-info/METADATA
pg_easy_bot-0.2.6.dist-info/WHEEL
pg_easy_bot-0.2.6.dist-info/top_level.txt
pg_easy_bot-0.2.6.dist-info/RECORD
