Metadata-Version: 2.1
Name: pg-easy-bot
Version: 0.2.6
Summary: A module for create pyrogram bot with easy and fast
Author: Pamod Madubahana
Author-email: premiumqtrst@gmail.com
Keywords: python,telegram bot,Easy Bots
Classifier: Development Status :: 1 - Planning
Classifier: Intended Audience :: Developers
Classifier: Programming Language :: Python :: 3
Classifier: Operating System :: OS Independent
License-File: LICENSE
Requires-Dist: pyrofork
Requires-Dist: TgCrypto
Requires-Dist: pymongo
Requires-Dist: psutil
Requires-Dist: requests
Requires-Dist: aiohttp
